aurorastack/__init__.py
aurorastack/core/__init__.py
aurorastack/core/base.py
aurorastack/core/command.py
aurorastack/core/error.py
aurorastack/core/locator.py
aurorastack/core/manager.py
aurorastack/core/token.py
aurorastack/core/transaction.py
aurorastack/core/utils.py
aurorastack/core/auth/__init__.py
aurorastack/core/auth/jwt/__init__.py
aurorastack/core/auth/jwt/jwt_util.py
aurorastack/core/cache/__init__.py
aurorastack/core/cache/base_cache.py
aurorastack/core/cache/local_cache.py
aurorastack/core/cache/redis_cache.py
aurorastack/core/config/__init__.py
aurorastack/core/config/default_conf.py
aurorastack/core/connector/__init__.py
aurorastack/core/connector/aurora_connector.py
aurorastack/core/fastapi/__init__.py
aurorastack/core/fastapi/api.py
aurorastack/core/fastapi/server.py
aurorastack/core/fastapi/extension/__init__.py
aurorastack/core/fastapi/extension/health.py
aurorastack/core/fastapi/extension/reflection.py
aurorastack/core/handler/__init__.py
aurorastack/core/handler/authentication_handler.py
aurorastack/core/handler/authorization_handler.py
aurorastack/core/handler/event_handler.py
aurorastack/core/handler/mutation_handler.py
aurorastack/core/logger/__init__.py
aurorastack/core/logger/filters/__init__.py
aurorastack/core/logger/filters/error.py
aurorastack/core/logger/filters/exclude.py
aurorastack/core/logger/filters/masking.py
aurorastack/core/logger/filters/message.py
aurorastack/core/logger/filters/parameter.py
aurorastack/core/logger/filters/traceback.py
aurorastack/core/logger/filters/transaction.py
aurorastack/core/model/__init__.py
aurorastack/core/model/base_model.py
aurorastack/core/model/mongo_model/__init__.py
aurorastack/core/model/mongo_model/filter_operator.py
aurorastack/core/model/mongo_model/stat_operator.py
aurorastack/core/opentelemetry/__init__.py
aurorastack/core/opentelemetry/metrics.py
aurorastack/core/opentelemetry/tracer.py
aurorastack/core/plugin/__init__.py
aurorastack/core/plugin/plugin_conf.py
aurorastack_core-0.0.2.dist-info/METADATA
aurorastack_core-0.0.2.dist-info/WHEEL
aurorastack_core-0.0.2.dist-info/entry_points.txt
aurorastack_core-0.0.2.dist-info/licenses/LICENSE
aurorastack_core-0.0.2.dist-info/RECORD
