Metadata-Version: 2.1
Name: aurorastack-core
Version: 0.0.2
Summary: MSA framework with kubernetes
Project-URL: Homepage, https://aurorastack.io
Project-URL: Documentation, https://aurorastack.io
Project-URL: Repository, https://github.com/aurorastack/aurorastack-core.git
Project-URL: Bug Tracker, https://github.com/aurorastack/issues
Project-URL: Changelog, https://github.com/aurorastack/aurorastack-core/blob/master/CHANGELOG.md
Author-email: Choonho Son <choonho.son@advancd.ai>, Jongmin Kim <whdalsrnt@megazone.com>
Maintainer-email: Choonho Son <choonho.son@advancd.ai>
License:                                  Apache License
License-File: LICENSE
Keywords: MSA,fastapi,gRPC,kubernetes,scheduler,worker
Classifier: Development Status :: 3 - Alpha
Classifier: Intended Audience :: Developers
Classifier: Programming Language :: Python :: 3.8
Classifier: Programming Language :: Python :: 3.9
Requires-Python: >=3.8
Requires-Dist: asyncio
Requires-Dist: cachetools
Requires-Dist: click
Requires-Dist: dnspython
Requires-Dist: factory-boy
Requires-Dist: fastapi
Requires-Dist: fastapi-utils
Requires-Dist: google-api-core
Requires-Dist: grpcio-health-checking
Requires-Dist: grpcio-reflection
Requires-Dist: jsonschema
Requires-Dist: jwcrypto
Requires-Dist: mongoengine
Requires-Dist: mongomock
Requires-Dist: opentelemetry-api
Requires-Dist: opentelemetry-exporter-otlp-proto-grpc
Requires-Dist: opentelemetry-exporter-prometheus
Requires-Dist: opentelemetry-instrumentation-logging
Requires-Dist: opentelemetry-sdk
Requires-Dist: protobuf==3.*
Requires-Dist: pycryptodome
Requires-Dist: pydantic
Requires-Dist: python-consul
Requires-Dist: python-dateutil
Requires-Dist: python-jose
Requires-Dist: pyyaml
Requires-Dist: redis
Requires-Dist: requests
Requires-Dist: schedule
Requires-Dist: scheduler-cron
Requires-Dist: unittest-xml-reporting
Requires-Dist: uvicorn
